es_stats_zabbix/__init__.py
es_stats_zabbix/__main__.py
es_stats_zabbix/_version.py
es_stats_zabbix/es_stats_zabbix.py
es_stats_zabbix/utils.py
es_stats_zabbix-0.1.3.dist-info/DESCRIPTION.rst
es_stats_zabbix-0.1.3.dist-info/METADATA
es_stats_zabbix-0.1.3.dist-info/RECORD
es_stats_zabbix-0.1.3.dist-info/WHEEL
es_stats_zabbix-0.1.3.dist-info/entry_points.txt
es_stats_zabbix-0.1.3.dist-info/metadata.json
es_stats_zabbix-0.1.3.dist-info/top_level.txt
