Metadata-Version: 2.0
Name: es-stats-zabbix
Version: 0.1.3
Summary: Collect stats from es_stats for ingest by Zabbix 
Home-page: http://github.com/untergeek/es_stats_zabbix
Author: Aaron Mildenstein
Author-email: aaron@mildensteins.com
License: Apache License, Version 2.0
Download-URL: https://github.com/untergeek/es_stats_zabbix/tarball/v0.1.3
Keywords: elasticsearch stats
Platform: UNKNOWN
Classifier: Intended Audience :: Developers
Classifier: Intended Audience :: System Administrators
Classifier: License :: OSI Approved :: Apache Software License
Requires-Dist: click (>=3.3)
Requires-Dist: elasticsearch (>=1.6.0)
Requires-Dist: es-stats (>=0.1.0)
Requires-Dist: kaptan (>=0.5.8)
Requires-Dist: zbxsend (>=0.1.6)
